archiveswurm/__init__.py
archiveswurm/__version__.py
archiveswurm/accession/__init__.py
archiveswurm/accession/accession.py
archiveswurm/agent/__init__.py
archiveswurm/agent/agent.py
archiveswurm/archivalobject/__init__.py
archiveswurm/archivalobject/archivalobject.py
archiveswurm/archivesspace/__init__.py
archiveswurm/archivesspace/archivesspace.py
archiveswurm/digitalcomponent/__init__.py
archiveswurm/digitalcomponent/digitalcomponent.py
archiveswurm/digitalobject/__init__.py
archiveswurm/digitalobject/digitalobject.py
archiveswurm/event/__init__.py
archiveswurm/event/event.py
archiveswurm/models/__init__.py
archiveswurm/models/models.py
archiveswurm/repository/__init__.py
archiveswurm/repository/repository.py
archiveswurm/resource/__init__.py
archiveswurm/resource/resource.py
archiveswurm/user/__init__.py
archiveswurm/user/user.py
archiveswurm-0.2.0.dist-info/METADATA
archiveswurm-0.2.0.dist-info/WHEEL
archiveswurm-0.2.0.dist-info/RECORD
